botm/__init__.py
botm/errors/__init__.py
botm/errors/already_running_error.py
botm/errors/not_running_error.py
botm/models/__init__.py
botm/models/bot_script.py
botm/models/abc/__init__.py
botm/models/abc/bot_process.py
botm/models/dataclasses/__init__.py
botm/models/dataclasses/bot_information.py
botm-0.1.dev0.dist-info/DESCRIPTION.rst
botm-0.1.dev0.dist-info/METADATA
botm-0.1.dev0.dist-info/RECORD
botm-0.1.dev0.dist-info/WHEEL
botm-0.1.dev0.dist-info/metadata.json
botm-0.1.dev0.dist-info/top_level.txt
